statping/__init__.py
statping/checkins.py
statping/connection.py
statping/exceptions.py
statping/groups.py
statping/incidents.py
statping/messages.py
statping/miscellaneous.py
statping/notifiers.py
statping/oauth.py
statping/services.py
statping/statping.py
statping/theme.py
statping/users.py
pystatping-0.1.5.dist-info/AUTHORS.rst
pystatping-0.1.5.dist-info/LICENSE
pystatping-0.1.5.dist-info/METADATA
pystatping-0.1.5.dist-info/WHEEL
pystatping-0.1.5.dist-info/top_level.txt
pystatping-0.1.5.dist-info/RECORD
