Metadata-Version: 2.1
Name: pystatping
Version: 0.1.5
Summary: Statping API client library
Home-page: https://github.com/danielpalstra/pystatping
Author: Daniel Palstra
Author-email: daniel@danielpalstra.com
License: Apache Software License 2.0
Keywords: pystatping
Platform: UNKNOWN
Classifier: Development Status :: 2 - Pre-Alpha
Classifier: Intended Audience :: Developers
Classifier: License :: OSI Approved :: Apache Software License
Classifier: Natural Language :: English
Classifier: Programming Language :: Python :: 3
Classifier: Programming Language :: Python :: 3.5
Classifier: Programming Language :: Python :: 3.6
Classifier: Programming Language :: Python :: 3.7
Classifier: Programming Language :: Python :: 3.8
Requires-Python: >=3.5
Requires-Dist: requests (<3.0,>=2.25.0)
